{"resource": {
    "citation": "",
    "issn": "0021-8561",
    "location": {
        "vocabulary": "",
        "value": "",
        "uri": ""
    },
    "updatedDate": "2013-06-30T05:24:43Z",
    "rights": "CIMMYT manages Intellectual Assets as International Public Goods. The user is free to download, print, store and share this work. In case you want to translate or create any other derivative work and share or distribute such translation/derivative work, please contact CIMMYT-Knowledge-Center@cgiar.org indicating the work you want to use and the kind of use you intend; CIMMYT will contact you with the sutable license for that purpose.",
    "relation": "",
    "appid": "10883_3142",
    "collection": [
        {
            "id": 1403840553,
            "type": "collection",
            "uri": "/cimmyt/collection/1403840553"
        },
        {
            "id": 403613914,
            "type": "collection",
            "uri": "/cimmyt/collection/403613914"
        }
    ],
    "format": "",
    "type": "Journal article",
    "date": "2011",
    "url": [
        {
            "broken": false,
            "value": "http://hdl.handle.net/10883/3142"
        },
        {
            "broken": false,
            "value": "http://repository.cimmyt.org/xmlui/handle/10883/3142"
        }
    ],
    "appuri": "/cimmyt/resource/10883_3142",
    "creator": [
        {
            "id": 1743998512,
            "value": "Rosales, A.",
            "type": "person",
            "uri": "/cimmyt/person/1743998512"
        },
        {
            "id": 823974202,
            "value": "Galicia, L.",
            "type": "person",
            "uri": "/cimmyt/person/823974202"
        },
        {
            "id": 449107157,
            "value": "Oviedo, E.",
            "type": "person",
            "uri": "/cimmyt/person/449107157"
        },
        {
            "id": 289738029,
            "value": "Islas, C.",
            "type": "person",
            "uri": "/cimmyt/person/289738029"
        },
        {
            "id": 1516184394,
            "value": "Palacios-Rojas, N.",
            "type": "person",
            "uri": "/cimmyt/person/1516184394"
        }
    ],
    "publisher": {
        "id": "",
        "value": "",
        "type": "",
        "uri": ""
    },
    "aggregation": {
        "linkToResource": [
            {
                "category": "",
                "value": "http://repository.cimmyt.org/xmlui/bitstream/10883/3142/1/95582.pdf",
                "label": "",
                "type": "application/pdf",
                "size": 1116160
            },
            {
                "category": "",
                "value": "http://repository.cimmyt.org/xmlui/bitstream/10883/3142/2/95582.pdf.txt",
                "label": "",
                "type": "application/pdf",
                "size": 29174
            },
            {
                "category": "",
                "value": "http://repository.cimmyt.org/xmlui/bitstream/10883/3142/3/95582.pdf.jpg",
                "label": "",
                "type": "text/plain",
                "size": 18834
            }
        ],
        "shownBy": [
            {
                "broken": false,
                "value": "http://repository.cimmyt.org/xmlui/bitstream/10883/3142/1/95582.pdf"
            },
            {
                "broken": false,
                "value": "http://repository.cimmyt.org/xmlui/bitstream/10883/3142/2/95582.pdf.txt"
            },
            {
                "broken": false,
                "value": "http://repository.cimmyt.org/xmlui/bitstream/10883/3142/3/95582.pdf.jpg"
            }
        ],
        "shownAt": {
            "broken": false,
            "value": "http://repository.cimmyt.org/xmlui/handle/10883/3142"
        }
    },
    "extent": "",
    "page": "10781-10786",
    "coverage": "Global",
    "contributor": {
        "id": "",
        "value": "",
        "type": "",
        "uri": ""
    },
    "isbn": "",
    "quality": "",
    "place": "",
    "doi": ""
}}
