{"object": {
    "title": {
        "value": "Simulating response of maize to previous velvet bean (Mucuna pruriens) crop and nitrogen fertiliser in Malawi",
        "lang": "eng"
    },
    "updated": "2016-01-22T23:05:49Z",
    "created": "2013-06-05T15:45:30Z",
    "subject": [
        {
            "vocabulary": [
                "agrovoc",
                ""
            ],
            "score": [
                1,
                ""
            ],
            "value": "maize",
            "uri": [
                "http://aims.fao.org/aos/agrovoc/c_12332",
                ""
            ]
        },
        {
            "vocabulary": [
                "agrovoc",
                ""
            ],
            "score": [
                1,
                ""
            ],
            "value": "bean sprouts",
            "uri": [
                "http://aims.fao.org/aos/agrovoc/c_15889",
                ""
            ]
        },
        {
            "vocabulary": [
                "agrovoc",
                ""
            ],
            "score": [
                1,
                ""
            ],
            "value": "mucuna pruriens",
            "uri": [
                "http://aims.fao.org/aos/agrovoc/c_4971",
                ""
            ]
        },
        {
            "vocabulary": [
                "agrovoc",
                ""
            ],
            "score": [
                1,
                ""
            ],
            "value": "fertilizer application",
            "uri": [
                "http://aims.fao.org/aos/agrovoc/c_10795",
                ""
            ]
        },
        {
            "vocabulary": [
                "agrovoc",
                ""
            ],
            "score": [
                1,
                ""
            ],
            "value": "nitrogen content",
            "uri": [
                "http://aims.fao.org/aos/agrovoc/c_5193",
                ""
            ]
        },
        {
            "vocabulary": "",
            "score": "",
            "value": "crop yield",
            "uri": ""
        },
        {
            "vocabulary": "",
            "score": "",
            "value": "production economics",
            "uri": ""
        },
        {
            "vocabulary": "",
            "score": "",
            "value": "malawi",
            "uri": ""
        }
    ],
    "description": {
        "value": "",
        "lang": ""
    },
    "appid": "10883_1459",
    "language": {
        "value": "eng",
        "uri": "http://lexvo.org/id/iso639-3/eng"
    },
    "type": "resource",
    "appuri": "/cimmyt/resource/10883_1459"
}}
