{"object": {
    "title": {
        "value": "Maladies et ravageurs du ble: Guide d'identification au champ",
        "lang": "fra"
    },
    "updated": "2015-05-28T17:12:06Z",
    "created": "2014-03-13T01:09:34Z",
    "subject": [
        {
            "vocabulary": "",
            "score": "",
            "value": "plant disease manifestations",
            "uri": ""
        },
        {
            "vocabulary": [
                "agrovoc",
                ""
            ],
            "score": [
                1,
                ""
            ],
            "value": "wheats",
            "uri": [
                "http://aims.fao.org/aos/agrovoc/c_8373",
                ""
            ]
        },
        {
            "vocabulary": "",
            "score": "",
            "value": "triticales",
            "uri": ""
        },
        {
            "vocabulary": "",
            "score": "",
            "value": "aphids",
            "uri": ""
        },
        {
            "vocabulary": "",
            "score": "",
            "value": "pest insects",
            "uri": ""
        },
        {
            "vocabulary": "",
            "score": "",
            "value": "nematoda",
            "uri": ""
        },
        {
            "vocabulary": "",
            "score": "",
            "value": "functional disorders",
            "uri": ""
        },
        {
            "vocabulary": "",
            "score": "",
            "value": "genetic disorders",
            "uri": ""
        },
        {
            "vocabulary": "",
            "score": "",
            "value": "identification",
            "uri": ""
        },
        {
            "vocabulary": "",
            "score": "",
            "value": "diagnosis",
            "uri": ""
        }
    ],
    "description": {
        "value": "",
        "lang": ""
    },
    "appid": "10883_3871",
    "language": {
        "value": "fra",
        "uri": "http://lexvo.org/id/iso639-3/fra"
    },
    "type": "resource",
    "appuri": "/cimmyt/resource/10883_3871"
}}
