{"person": {
    "lastName": "Mafongoya",
    "shortBio": "",
    "orcid": "",
    "location": {
        "vocabulary": "",
        "value": "",
        "uri": ""
    },
    "appid": 110558603,
    "affiliation": {
        "id": "",
        "value": "",
        "type": "",
        "uri": ""
    },
    "fullName": "Mafongoya, P.L.",
    "firstName": "P.L.",
    "photo": "",
    "contact": "",
    "url": {
        "broken": false,
        "value": ""
    },
    "appuri": "/cimmyt/person/110558603"
}}
