{"person": {
    "lastName": "Berthaud",
    "shortBio": "",
    "orcid": "",
    "location": {
        "vocabulary": "",
        "value": "",
        "uri": ""
    },
    "appid": 1112460347,
    "affiliation": {
        "id": "",
        "value": "",
        "type": "",
        "uri": ""
    },
    "fullName": "Berthaud, J.",
    "firstName": "J.",
    "photo": "",
    "contact": "",
    "url": {
        "broken": false,
        "value": ""
    },
    "appuri": "/cimmyt/person/1112460347"
}}
