{"person": {
    "lastName": "Eriksson",
    "shortBio": "",
    "orcid": "",
    "location": {
        "vocabulary": "",
        "value": "",
        "uri": ""
    },
    "appid": 1131199156,
    "affiliation": {
        "id": "",
        "value": "",
        "type": "",
        "uri": ""
    },
    "fullName": "Eriksson, D.",
    "firstName": "D.",
    "photo": "",
    "contact": "",
    "url": {
        "broken": false,
        "value": ""
    },
    "appuri": "/cimmyt/person/1131199156"
}}
