{"person": {
    "lastName": "Yueming",
    "shortBio": "",
    "orcid": "http://orcid.org/0000-0002-2806-217X",
    "location": {
        "vocabulary": "",
        "value": "",
        "uri": ""
    },
    "appid": 1764656220,
    "affiliation": {
        "id": "",
        "value": "",
        "type": "",
        "uri": ""
    },
    "fullName": "Yueming Yan",
    "firstName": "Yan",
    "photo": "",
    "contact": "",
    "url": {
        "broken": false,
        "value": ""
    },
    "appuri": "/cimmyt/person/1764656220"
}}
