{"person": {
    "lastName": "Guerrero",
    "shortBio": "",
    "orcid": "",
    "location": {
        "vocabulary": "",
        "value": "",
        "uri": ""
    },
    "appid": 2146294405,
    "affiliation": {
        "id": "",
        "value": "",
        "type": "",
        "uri": ""
    },
    "fullName": "Guerrero, R.",
    "firstName": "R.",
    "photo": "",
    "contact": "",
    "url": {
        "broken": false,
        "value": ""
    },
    "appuri": "/cimmyt/person/2146294405"
}}
