{"person": {
    "lastName": "Wellhausen",
    "shortBio": "",
    "orcid": "",
    "location": {
        "vocabulary": "",
        "value": "",
        "uri": ""
    },
    "appid": 740752625,
    "affiliation": {
        "id": "",
        "value": "",
        "type": "",
        "uri": ""
    },
    "fullName": "Wellhausen, E.J.",
    "firstName": "E.J.",
    "photo": "",
    "contact": "",
    "url": {
        "broken": false,
        "value": ""
    },
    "appuri": "/cimmyt/person/740752625"
}}
