{"person": {
    "lastName": "Qinglin",
    "shortBio": "",
    "orcid": "http://orcid.org/0000-0002-5789-4653",
    "location": {
        "vocabulary": "",
        "value": "",
        "uri": ""
    },
    "appid": 990446903,
    "affiliation": {
        "id": "",
        "value": "",
        "type": "",
        "uri": ""
    },
    "fullName": "Qinglin Lu",
    "firstName": "Lu",
    "photo": "",
    "contact": "",
    "url": {
        "broken": false,
        "value": ""
    },
    "appuri": "/cimmyt/person/990446903"
}}
